Metadata-Version: 1.2
Name: printW
Version: 1.0.0
Summary: A typewrite for python
Home-page: https://github.com/batestin1/
Author: Maycon Cypriano Batestin
Author-email: mayconcipriano@gmail.com
License: UNKNOWN
Project-URL: Código fonte, https://github.com/batestin1/
Project-URL: Download, https://github.com/batestin1/
Keywords: A typewrite for python
Platform: UNKNOWN
